NumpyShuzuXuexiShouceChuyiFix1/README.md
NumpyShuzuXuexiShouceChuyiFix1/__init__.py
NumpyShuzuXuexiShouceChuyiFix1/__main__.py
NumpyShuzuXuexiShouceChuyiFix1/file.epub
NumpyShuzuXuexiShouceChuyiFix1/index.html
NumpyShuzuXuexiShouceChuyiFix1/css/__init__.py
NumpyShuzuXuexiShouceChuyiFix1/css/annotations.css
NumpyShuzuXuexiShouceChuyiFix1/css/main.css
NumpyShuzuXuexiShouceChuyiFix1/css/normalize.css
NumpyShuzuXuexiShouceChuyiFix1/css/popup.css
NumpyShuzuXuexiShouceChuyiFix1/font/__init__.py
NumpyShuzuXuexiShouceChuyiFix1/font/fontello.eot
NumpyShuzuXuexiShouceChuyiFix1/font/fontello.svg
NumpyShuzuXuexiShouceChuyiFix1/font/fontello.ttf
NumpyShuzuXuexiShouceChuyiFix1/font/fontello.woff
NumpyShuzuXuexiShouceChuyiFix1/img/__init__.py
NumpyShuzuXuexiShouceChuyiFix1/img/annotator-glyph-sprite.png
NumpyShuzuXuexiShouceChuyiFix1/img/annotator-icon-sprite.png
NumpyShuzuXuexiShouceChuyiFix1/img/apple-touch-icon.png
NumpyShuzuXuexiShouceChuyiFix1/img/cancelfullscreen.png
NumpyShuzuXuexiShouceChuyiFix1/img/close.png
NumpyShuzuXuexiShouceChuyiFix1/img/fullscreen.png
NumpyShuzuXuexiShouceChuyiFix1/img/loader.gif
NumpyShuzuXuexiShouceChuyiFix1/img/menu-icon.png
NumpyShuzuXuexiShouceChuyiFix1/img/save.png
NumpyShuzuXuexiShouceChuyiFix1/img/saved.png
NumpyShuzuXuexiShouceChuyiFix1/img/settings-s.png
NumpyShuzuXuexiShouceChuyiFix1/img/settings.png
NumpyShuzuXuexiShouceChuyiFix1/img/star.png
NumpyShuzuXuexiShouceChuyiFix1/js/__init__.py
NumpyShuzuXuexiShouceChuyiFix1/js/epub.js
NumpyShuzuXuexiShouceChuyiFix1/js/epub.min.js
NumpyShuzuXuexiShouceChuyiFix1/js/epub.min.map
NumpyShuzuXuexiShouceChuyiFix1/js/hooks.min.js
NumpyShuzuXuexiShouceChuyiFix1/js/hooks.min.map
NumpyShuzuXuexiShouceChuyiFix1/js/reader.js
NumpyShuzuXuexiShouceChuyiFix1/js/reader.js.map
NumpyShuzuXuexiShouceChuyiFix1/js/reader.min.js
NumpyShuzuXuexiShouceChuyiFix1/js/reader.min.map
NumpyShuzuXuexiShouceChuyiFix1/js/hooks/__init__.py
NumpyShuzuXuexiShouceChuyiFix1/js/hooks/extensions/__init__.py
numpy_shuzu_xuexi_shouce_chuyi_fix1-2025.3.24.0.dist-info/METADATA
numpy_shuzu_xuexi_shouce_chuyi_fix1-2025.3.24.0.dist-info/WHEEL
numpy_shuzu_xuexi_shouce_chuyi_fix1-2025.3.24.0.dist-info/entry_points.txt
numpy_shuzu_xuexi_shouce_chuyi_fix1-2025.3.24.0.dist-info/top_level.txt
numpy_shuzu_xuexi_shouce_chuyi_fix1-2025.3.24.0.dist-info/RECORD
